MANIFEST.in
README.rst
setup.py
aliyun_python_sdk_faas.egg-info/PKG-INFO
aliyun_python_sdk_faas.egg-info/SOURCES.txt
aliyun_python_sdk_faas.egg-info/dependency_links.txt
aliyun_python_sdk_faas.egg-info/requires.txt
aliyun_python_sdk_faas.egg-info/top_level.txt
aliyunsdkfaas/__init__.py
aliyunsdkfaas/endpoint.py
aliyunsdkfaas/request/__init__.py
aliyunsdkfaas/request/v20170824/CreateFpgaImageTaskRequest.py
aliyunsdkfaas/request/v20170824/DeleteFpgaImageRequest.py
aliyunsdkfaas/request/v20170824/DeletePublishFpgaImageRequest.py
aliyunsdkfaas/request/v20170824/DescribeFpgaImagesRequest.py
aliyunsdkfaas/request/v20170824/DescribeFpgaInstancesRequest.py
aliyunsdkfaas/request/v20170824/DescribeLoadTaskStatusRequest.py
aliyunsdkfaas/request/v20170824/DescribePublishFpgaImagesRequest.py
aliyunsdkfaas/request/v20170824/LoadFpgaImageTaskRequest.py
aliyunsdkfaas/request/v20170824/PublishFpgaImageRequest.py
aliyunsdkfaas/request/v20170824/PullCreateTaskRequest.py
aliyunsdkfaas/request/v20170824/UpdateCreateTaskRequest.py
aliyunsdkfaas/request/v20170824/UpdateImageAttributeRequest.py
aliyunsdkfaas/request/v20170824/__init__.py
aliyunsdkfaas/request/v20200217/UpdateCompilerStatusRequest.py
aliyunsdkfaas/request/v20200217/__init__.py